nawa/__init__.py
nawa/behavior.py
nawa/matcher.py
nawa/report.py
nawa/utils.py
nawa_tracking-0.1.0.dist-info/licenses/LICENSE
nawa_tracking-0.1.0.dist-info/METADATA
nawa_tracking-0.1.0.dist-info/WHEEL
nawa_tracking-0.1.0.dist-info/top_level.txt
nawa_tracking-0.1.0.dist-info/RECORD
